hoist/__init__.py
hoist/__main__.py
hoist/util.py
hoist/web_files/asset-manifest.json
hoist/web_files/favicon.ico
hoist/web_files/index.html
hoist/web_files/manifest.json
hoist/web_files/precache-manifest.aa20685a6206e3acf7c0796e9d63e96d.js
hoist/web_files/service-worker.js
hoist/web_files/static/css/main.a5870b6d.chunk.css
hoist/web_files/static/css/main.a5870b6d.chunk.css.map
hoist/web_files/static/js/2.deb8772f.chunk.js
hoist/web_files/static/js/2.deb8772f.chunk.js.map
hoist/web_files/static/js/main.59cfe229.chunk.js
hoist/web_files/static/js/main.59cfe229.chunk.js.map
hoist/web_files/static/js/runtime~main.a8a9905a.js
hoist/web_files/static/js/runtime~main.a8a9905a.js.map
hoist-0.1.2.dist-info/entry_points.txt
hoist-0.1.2.dist-info/LICENSE.md
hoist-0.1.2.dist-info/WHEEL
hoist-0.1.2.dist-info/METADATA
hoist-0.1.2.dist-info/RECORD
