Metadata-Version: 2.1
Name: hoist
Version: 0.1.2
Summary: 
Home-page: UNKNOWN
License: UNKNOWN
Author: Shady Rafehi
Author-email: shadyrafehi@gmail.com
Requires-Python: >=3.6,<4.0
Classifier: Programming Language :: Python :: 3
Classifier: Programming Language :: Python :: 3.6
Classifier: Programming Language :: Python :: 3.7
Requires-Dist: aiohttp (>=3.5,<4.0)
Requires-Dist: jinja2 (>=2.10,<3.0)
Requires-Dist: toml (>=0.10.0,<0.11.0)
Requires-Dist: websockets (>=7.0,<8.0)
